jSona/__init__.py
jSona/core/__init__.py
jSona/core/parser.py
jSona/demo/__init__.py
jSona/demo/demo.py
jSona-3.1.dist-info/LICENSE
jSona-3.1.dist-info/METADATA
jSona-3.1.dist-info/WHEEL
jSona-3.1.dist-info/top_level.txt
jSona-3.1.dist-info/RECORD
