Metadata-Version: 2.1
Name: jSona
Version: 3.1
Summary: JSON format handler on the json built-in module
Home-page: https://github.com/oimq/jSona
Author: oimq
Author-email: taep0q@gmail.com
License: MIT
Platform: UNKNOWN
Classifier: Programming Language :: Python :: 3
Classifier: License :: OSI Approved :: MIT License
Classifier: Operating System :: OS Independent
